plexers/decoder/decoder.v
// 8-1 decoder

module decoder(
    input wire [2:0] sel,
    input wire oe,

    output wire a,
    output wire b,
    output wire c,
    output wire d,
    output wire e,
    output wire f,
    output wire g,
    output wire h
);

    assign {h,g,f,e,d,c,b,a} = oe ? (1 << sel) : 8'b0;
    // oe = output enable | if oe is 1, then the output is sel, else all outputs are 0
    // (1 << sel) shifts 1 to the left by the value of sel, creating a binary number with one bit set

    /*
    sel = 0: 1 << 0 = 00000001  // 1 moves to position 1  
    sel = 5: 1 << 5 = 00010000  // 1 moves to position 5
    sel = 3: 1 << 3 = 00001000  // 1 moves to position 3

    it gets shifted by the value of sel
    */

endmodule

plexers/decoder/decoder_tb.v
// 8-1 decoder

module decoder_tb;

    reg [2:0] sel;
    reg oe;
    wire a, b, c, d, e, f, g, h;

    decoder uut(.sel(sel), .oe(oe), .a(a), .b(b), .c(c), .d(d), .e(e), .f(f), .g(g), .h(h));

    initial begin
        $dumpfile("decoder.vcd");
        $dumpvars(0, decoder_tb);


        sel = 3'b000; oe = 1; #10;
        sel = 3'b001; oe = 1; #10;
        sel = 3'b010; oe = 1; #10;
        sel = 3'b011; oe = 1; #10;
        sel = 3'b100; oe = 1; #10;
        sel = 3'b101; oe = 1; #10;
        sel = 3'b110; oe = 1; #10;
        sel = 3'b111; oe = 1; #10;
        
        sel = 3'b000; oe = 0; #10;
        sel = 3'b001; oe = 0; #10;
        sel = 3'b010; oe = 0; #10;
        sel = 3'b011; oe = 0; #10;
        sel = 3'b100; oe = 0; #10;
        sel = 3'b101; oe = 0; #10;
        sel = 3'b110; oe = 0; #10;
        sel = 3'b111; oe = 0; #10;

        $finish;
    end

endmodule

plexers/decoder/decoder.vcd
$date
	Wed Jul 30 12:52:48 2025
$end
$version
	Icarus Verilog
$end
$timescale
	1s
$end
$scope module decoder_tb $end
$var wire 1 ! h $end
$var wire 1 " g $end
$var wire 1 # f $end
$var wire 1 $ e $end
$var wire 1 % d $end
$var wire 1 & c $end
$var wire 1 ' b $end
$var wire 1 ( a $end
$var reg 1 ) oe $end
$var reg 3 * sel [2:0] $end
$scope module uut $end
$var wire 1 ) oe $end
$var wire 3 + sel [2:0] $end
$var wire 1 ! h $end
$var wire 1 " g $end
$var wire 1 # f $end
$var wire 1 $ e $end
$var wire 1 % d $end
$var wire 1 & c $end
$var wire 1 ' b $end
$var wire 1 ( a $end
$upscope $end
$upscope $end
$enddefinitions $end
$comment Show the parameter values. $end
$dumpall
$end
#0
$dumpvars
b0 +
b0 *
1)
1(
0'
0&
0%
0$
0#
0"
0!
$end
#10
0(
1'
b1 *
b1 +
#20
0'
1&
b10 *
b10 +
#30
0&
1%
b11 *
b11 +
#40
0%
1$
b100 *
b100 +
#50
0$
1#
b101 *
b101 +
#60
0#
1"
b110 *
b110 +
#70
0"
1!
b111 *
b111 +
#80
0!
0)
b0 *
b0 +
#90
b1 *
b1 +
#100
b10 *
b10 +
#110
b11 *
b11 +
#120
b100 *
b100 +
#130
b101 *
b101 +
#140
b110 *
b110 +
#150
b111 *
b111 +
