plexers/multiplexer/multiplexer.v
// 3-8 multiplexer specifically

module multiplexer(

    input wire a,
    input wire b,
    input wire c,
    input wire d,
    input wire e,
    input wire f,
    input wire g,
    input wire h,

    input wire [2:0] sel,

    output wire y
);

    assign y = (sel[2] == 1) ? ((sel[1] == 1) ? ((sel[0] == 1) ? h : g) : ((sel[0] == 1) ? f : e)) : ((sel[1] == 1) ? ((sel[0] == 1) ? d : c) : ((sel[0] == 1) ? b : a));
    // sel binary 000-111 (0-7)   |   (x ? y : z) = (if statement ? true : false)
endmodule

plexers/multiplexer/multiplexer_tb.v
// 3-8 multiplexer specifically

module multiplexer_tb;

    reg a, b, c, d, e, f, g, h;
    reg [2:0] sel;
    wire y;

    multiplexer uut(.a(a), .b(b), .c(c), .d(d), .e(e), .f(f), .g(g), .h(h), .sel(sel), .y(y));

    initial begin
        $dumpfile("multiplexer.vcd");
        $dumpvars(0, multiplexer_tb);

        a = 0; b = 1; c = 1; d = 1; e = 0; f = 0; g = 1; h = 0; sel = 3'b000; #10
        a = 1; b = 1; c = 0; d = 1; e = 1; f = 0; g = 1; h = 1; sel = 3'b001; #10
        a = 0; b = 0; c = 1; d = 0; e = 1; f = 1; g = 1; h = 1; sel = 3'b010; #10
        a = 1; b = 0; c = 1; d = 0; e = 0; f = 1; g = 1; h = 0; sel = 3'b011; #10
        a = 1; b = 1; c = 1; d = 0; e = 0; f = 0; g = 0; h = 1; sel = 3'b100; #10
        a = 1; b = 0; c = 0; d = 1; e = 0; f = 0; g = 0; h = 0; sel = 3'b101; #10
        a = 1; b = 0; c = 1; d = 0; e = 0; f = 1; g = 0; h = 1; sel = 3'b110; #10
        a = 0; b = 1; c = 1; d = 0; e = 0; f = 1; g = 0; h = 0; sel = 3'b111; #10
                                // 3 bit values | 'b = binary | what bits are what
        $finish;
    end

endmodule

plexers/multiplexer/multiplexer.vcd
$date
	Wed Jul 30 12:16:50 2025
$end
$version
	Icarus Verilog
$end
$timescale
	1s
$end
$scope module multiplexer_tb $end
$var wire 1 ! y $end
$var reg 1 " a $end
$var reg 1 # b $end
$var reg 1 $ c $end
$var reg 1 % d $end
$var reg 1 & e $end
$var reg 1 ' f $end
$var reg 1 ( g $end
$var reg 1 ) h $end
$var reg 3 * sel [2:0] $end
$scope module uut $end
$var wire 1 " a $end
$var wire 1 # b $end
$var wire 1 $ c $end
$var wire 1 % d $end
$var wire 1 & e $end
$var wire 1 ' f $end
$var wire 1 ( g $end
$var wire 1 ) h $end
$var wire 3 + sel [2:0] $end
$var wire 1 ! y $end
$upscope $end
$upscope $end
$enddefinitions $end
$comment Show the parameter values. $end
$dumpall
$end
#0
$dumpvars
b0 +
b0 *
0)
1(
0'
0&
1%
1$
1#
0"
0!
$end
#10
1!
b1 *
b1 +
1)
1&
0$
1"
#20
1!
b10 *
b10 +
1'
0%
1$
0#
0"
#30
0!
b11 *
b11 +
0)
0&
1"
#40
b100 *
b100 +
1)
0(
0'
1#
#50
b101 *
b101 +
0)
1%
0$
0#
#60
0!
b110 *
b110 +
1)
1'
0%
1$
#70
b111 *
b111 +
0)
1#
0"
